ptk/__init__.py
ptk/timeseries/__init__.py
ptk/timeseries/timeseries.py
ptk/utils/__init__.py
ptk/utils/numpytools.py
ptk/utils/torchtools.py
ptk/utils/utils.py
ptk_patrickctrf-0.1.2.dist-info/LICENSE
ptk_patrickctrf-0.1.2.dist-info/METADATA
ptk_patrickctrf-0.1.2.dist-info/WHEEL
ptk_patrickctrf-0.1.2.dist-info/top_level.txt
ptk_patrickctrf-0.1.2.dist-info/RECORD
