Metadata-Version: 2.1
Name: ptk-patrickctrf
Version: 0.1.2
Summary: Package for Python programming by Patrick Ferreira
Home-page: https://github.com/patrickctrf/ptk
Author: patrickctrf
Author-email: patrickctrf@gmail.com
Classifier: Programming Language :: Python :: 3
Classifier: License :: OSI Approved :: MIT License
Classifier: Operating System :: OS Independent
Requires-Python: >=3.6
License-File: LICENSE
Requires-Dist: numpy
Requires-Dist: torch
Requires-Dist: tensorflow
